{
  "joke": {
    "seed_id": "seed-197",
    "source": "csv-import",
    "url": "",
    "raw_joke": "I would like to thank my arms, my legs, and my fingers \u2014 for always being by my side, always supporting me, and always knowing that I can count on them.",
    "theme": "",
    "caption_safe": "unknown",
    "originality_risk": "unknown",
    "status": "backburner",
    "rewrite_status": "",
    "created_at": "2026-03-18T23:26:26.667067+00:00",
    "updated_at": "2026-03-18T23:26:26.667067+00:00"
  },
  "blocks": []
}